textflint/__init__.py
textflint/adapter.py
textflint/engine.py
textflint/textflint_cli.py
textflint/common/__init__.py
textflint/common/settings.py
textflint/common/preprocess/__init__.py
textflint/common/preprocess/cn_processor.py
textflint/common/preprocess/en_processor.py
textflint/common/preprocess/nltk_res_load.py
textflint/common/utils/__init__.py
textflint/common/utils/c_overlap_templates.py
textflint/common/utils/cn_num_word.py
textflint/common/utils/error.py
textflint/common/utils/file_io.py
textflint/common/utils/format_change.py
textflint/common/utils/fp_utils.py
textflint/common/utils/importing.py
textflint/common/utils/install.py
textflint/common/utils/list_op.py
textflint/common/utils/load.py
textflint/common/utils/logger.py
textflint/common/utils/num_word.py
textflint/common/utils/overlap_templates.py
textflint/common/utils/seed.py
textflint/common/utils/shift_utils.py
textflint/common/utils/word_op.py
textflint/generation/__init__.py
textflint/generation/attack/__init__.py
textflint/generation/attack/attack.py
textflint/generation/generator/__init__.py
textflint/generation/generator/absa_generator.py
textflint/generation/generator/coref_generator.py
textflint/generation/generator/cws_generator.py
textflint/generation/generator/dp_generator.py
textflint/generation/generator/dpcn_generator.py
textflint/generation/generator/generator.py
textflint/generation/generator/mrc_generator.py
textflint/generation/generator/mrccn_generator.py
textflint/generation/generator/ner_generator.py
textflint/generation/generator/nercn_generator.py
textflint/generation/generator/nli_generator.py
textflint/generation/generator/nmt_generator.py
textflint/generation/generator/pos_generator.py
textflint/generation/generator/re_generator.py
textflint/generation/generator/sa_generator.py
textflint/generation/generator/sacn_generator.py
textflint/generation/generator/sm_generator.py
textflint/generation/generator/smcn_generator.py
textflint/generation/generator/ut_generator.py
textflint-0.1.0.dist-info/LICENSE
textflint-0.1.0.dist-info/METADATA
textflint-0.1.0.dist-info/WHEEL
textflint-0.1.0.dist-info/entry_points.txt
textflint-0.1.0.dist-info/top_level.txt
textflint-0.1.0.dist-info/RECORD
