Metadata-Version: 2.1
Name: textflint
Version: 0.1.0
Summary: Unified Multilingual Robustness Evaluation Toolkit for Natural Language Processing
Home-page: https://github.com/textflint/textflint
Author: Fudan NLP Team
Author-email: xiao_wang20@fudan.edu.cn
License: GNU GENERAL PUBLIC LICENSE
Platform: UNKNOWN
Requires-Python: >=3.7
License-File: LICENSE
Requires-Dist: importlib-metadata (==3.2.0)
Requires-Dist: click (==7.1.1)
Requires-Dist: editdistance
Requires-Dist: nltk (==3.6.3)
Requires-Dist: pandas (>=1.0.1)
Requires-Dist: scikit-learn
Requires-Dist: torch
Requires-Dist: transformers
Requires-Dist: datasets
Requires-Dist: tokenizers
Requires-Dist: ltp
Requires-Dist: spacy (>=3.0.0)
Requires-Dist: morfessor
Requires-Dist: flashtext
Requires-Dist: wikidata
Requires-Dist: fuzzywuzzy
Requires-Dist: plotly
Requires-Dist: pypinyin
Requires-Dist: Pinyin2Hanzi
